latch/__init__.py
latch/account.py
latch/executions.py
latch/py.typed
latch/utils.py
latch/functions/__init__.py
latch/functions/messages.py
latch/functions/operators.py
latch/functions/secrets.py
latch/idl/utils.py
latch/idl/admin/common.py
latch/idl/admin/launch_plan.py
latch/idl/admin/schedule.py
latch/idl/admin/workflow.py
latch/idl/core/condition.py
latch/idl/core/execution.py
latch/idl/core/identifier.py
latch/idl/core/interface.py
latch/idl/core/literals.py
latch/idl/core/security.py
latch/idl/core/tasks.py
latch/idl/core/types.py
latch/idl/core/workflow.py
latch/ldata/__init__.py
latch/ldata/path.py
latch/ldata/type.py
latch/ldata/_transfer/__init__.py
latch/ldata/_transfer/download.py
latch/ldata/_transfer/manager.py
latch/ldata/_transfer/node.py
latch/ldata/_transfer/progress.py
latch/ldata/_transfer/remote_copy.py
latch/ldata/_transfer/throttle.py
latch/ldata/_transfer/upload.py
latch/ldata/_transfer/utils.py
latch/registry/__init__.py
latch/registry/project.py
latch/registry/record.py
latch/registry/table.py
latch/registry/types.py
latch/registry/utils.py
latch/registry/upstream_types/__init__.py
latch/registry/upstream_types/types.py
latch/registry/upstream_types/values.py
latch/resources/__init__.py
latch/resources/conditional.py
latch/resources/dynamic.py
latch/resources/launch_plan.py
latch/resources/map_tasks.py
latch/resources/reference_workflow.py
latch/resources/tasks.py
latch/resources/workflow.py
latch/types/__init__.py
latch/types/directory.py
latch/types/file.py
latch/types/glob.py
latch/types/json.py
latch/types/metadata.py
latch/types/plots.py
latch/types/samplesheet_item.py
latch/types/utils.py
latch/verified/__init__.py
latch/verified/deseq2.py
latch/verified/mafft.py
latch/verified/pathway.py
latch/verified/rnaseq.py
latch/verified/trim_galore.py
latch_cli/__init__.py
latch_cli/click_utils.py
latch_cli/constants.py
latch_cli/main.py
latch_cli/menus.py
latch_cli/py.typed
latch_cli/tinyrequests.py
latch_cli/workflow_config.py
latch-2.67.22.dist-info/METADATA
latch-2.67.22.dist-info/WHEEL
latch-2.67.22.dist-info/entry_points.txt
latch-2.67.22.dist-info/licenses/LICENSE
latch-2.67.22.dist-info/RECORD
