Metadata-Version: 2.4
Name: latch
Version: 2.67.22
Summary: The Latch SDK
Project-URL: Homepage, https://latch.bio
Project-URL: Documentation, https://latch.wiki
Project-URL: Repository, https://github.com/latchbio/latch
Project-URL: Issues, https://github.com/latchbio/latch/issues
Project-URL: Changelog, https://github.com/latchbio/latch/blob/main/CHANGELOG.md
Author-email: Kenny Workman <kenny@latch.bio>
Maintainer-email: Ayush Kamat <ayush@latch.bio>
License: Copyright 2024 LatchBio
License-File: LICENSE
Classifier: Development Status :: 4 - Beta
Classifier: Intended Audience :: Developers
Classifier: Intended Audience :: Healthcare Industry
Classifier: Intended Audience :: Science/Research
Classifier: Programming Language :: Python :: 3
Classifier: Programming Language :: Python :: 3.9
Classifier: Programming Language :: Python :: 3.10
Classifier: Programming Language :: Python :: 3.11
Classifier: Programming Language :: Python :: 3.12
Classifier: Topic :: Scientific/Engineering
Classifier: Topic :: Scientific/Engineering :: Bio-Informatics
Classifier: Topic :: Software Development :: Build Tools
Requires-Python: >=3.9
Requires-Dist: aioconsole==0.6.1
Requires-Dist: apscheduler>=3.10.0
Requires-Dist: asyncssh==2.13.2
Requires-Dist: boto3>=1.26.0
Requires-Dist: click>=8.0
Requires-Dist: dill>=0.4.0
Requires-Dist: docker>=7.1.0
Requires-Dist: gitpython==3.1.40
Requires-Dist: gql==3.5.0
Requires-Dist: graphql-core==3.2.3
Requires-Dist: kubernetes>=24.2.0
Requires-Dist: latch-persistence>=0.1.5
Requires-Dist: lytekit==0.15.29
Requires-Dist: lytekitplugins-pods==0.7.4
Requires-Dist: orjson>=3.10.12
Requires-Dist: paramiko>=3.4.0
Requires-Dist: pyjwt>=0.2.0
Requires-Dist: python-dateutil>=2.8
Requires-Dist: pyxattr>=0.8.1
Requires-Dist: requests-toolbelt==1.0.0
Requires-Dist: requests>=2.28.1
Requires-Dist: scp>=0.14.0
Requires-Dist: setuptools>=75.3.0
Requires-Dist: tqdm>=4.63.0
Requires-Dist: typing-extensions>=4.12.0
Requires-Dist: watchfiles==0.19.0
Requires-Dist: websockets>=15.0.1
Provides-Extra: pandas
Requires-Dist: pandas>=2.0.0; extra == 'pandas'
Provides-Extra: snakemake
Requires-Dist: pulp<2.8,>=2.0; extra == 'snakemake'
Requires-Dist: snakemake<7.30.2,>=7.18.0; extra == 'snakemake'
